Workbook

Sheet 1. Maint Account
B1: Sl.No | C1: Date of Invoice | D1: Invoice Number | E1: Payment Date | F1: Service Month | G1: Quarter | H1: Vendor Name | I1: Particulars | J1: Classification-1 | K1: Taxable | L1: % | M1: Invoice Value | N1: TDS | O1: Net Paid | P1: Nature | Q1: Classification | T1: Total Expense Paid
B2: 1 | E2: 45751 | F2: 45748 | G2: Q4 FY 24-25 | H2: Mukajjar Smarttech India | I2: 30% payment for removal of chamber cover | J2: RWH Works | K2: 1568661 | M2: 1568661 | O2: 470598 | P2: Capex | Q2: Civil & Lifts | T2: =N2+O2 -> 470598
B3: 2 | C3: 25-03-2025 | D3: Quotation | E3: 45751 | F3: 45748 | G3: Q4 FY 24-25 | H3: S R Office Suppliers | I3: Sodium hypochlorites,test kit,waste cloth | J3: STP- Consumables | K3: 34460 | L3: 6164 | M3: 40624 | O3: 40624 | P3: Ad-Hoc | Q3: Water & Sewage | T3: =N3+O3 -> 40624
B4: 3 | D4: Quotation | E4: 45755 | F4: 45748 | G4: Q1 | H4: Blaze Design Tech | I4: 30% advance payment forSupply and installation of 30 Zone | J4: Fire Alarm Installation | K4: 637170 | M4: 637170 | O4: 191151 | P4: Capex | Q4: Safety & Security | T4: =N4+O4 -> 191151
B5: 4 | C5: 45745 | D5: 226/24-25 | E5: 45755 | F5: 45748 | G5: Q1 | H5: Mukajjar Smarttech India | I5: Supply and providing of new granite door seal | J5: Purchase of Granite | K5: 29700 | L5: 5346 | M5: 20196 | N5: 594 | O5: 19602 | P5: Ad-Hoc | Q5: Civil & Lifts | T5: =N5+O5 -> 20196
B6: 5 | C6: 45661 | D6: PTI202526-00914 | E6: 45755 | F6: 45748 | G6: Q1 | H6: Parivom Technologies Pvt Ltd | I6: Automated Gate and security solution | J6: Park-plus Services | K6: 125100 | L6: 22518 | M6: 147618 | N6: 2502 | O6: 145116 | P6: Capex | Q6: Safety & Security | T6: =N6+O6 -> 147618
B7: 6 | C7: 45661 | D7: KLKA2526-04055 | E7: 45755 | F7: 45717 | G7: Q4 FY 24-25 | H7: Kre38 Labs pvt ltd | I7: Waltr A monthly subscription | J7: Water Level Meters | K7: 8980 | L7: 1616 | M7: 10596 | N7: 180 | O7: 10417 | P7: Operating | Q7: Water & Sewage | T7: =N7+O7 -> 10597
B8: 7 | C8: 21-03-2025 | D8: OP/24-25/1643 | E8: 45755 | F8: 45748 | G8: Q1 | H8: Office point | I8: Box file YES955,Cello tape | J8: Housekeeping Consumables | K8: 27262 | L8: 3914 | M8: 31176 | O8: 31176 | P8: Ad-Hoc | Q8: Estate Management | T8: =N8+O8 -> 31176
B9: 8 | C9: 45661 | D9: IAC-17/2 | E9: 45755 | F9: 45717 | G9: Q4 FY 24-25 | H9: Think Thanx | I9: CCTV AMC charges for the month of March 2025 | J9: CCTV Maint | K9: 7500 | L9: 1350 | M9: 8850 | N9: 75 | O9: 8775 | P9: Operating | Q9: Safety & Security | T9: =N9+O9 -> 8850
B10: 9 | C10: 31-03-2025 | D10: 3015 | E10: 45757 | F10: 45717 | G10: Q4 FY 24-25 | H10: Sree Sai Ganesh Minerals | I10: 20L Water can | J10: Drinking Water Can | K10: 27636 | L10: 3316 | M10: 30952 | O10: 30952 | P10: Operating | Q10: Water & Sewage | T10: =N10+O10 -> 30952
B11: 10 | C11: 14-03-2025 | D11: OP/24-25/1618 | E11: 45757 | F11: 45748 | G11: Q1 | H11: Office Point | I11: Garbage Bag extra large pearl 40MIC | J11: Housekeeping Consumables | K11: 76968 | L11: 12739 | M11: 89707 | O11: 89707 | P11: Ad-Hoc | Q11: Estate Management | T11: =N11+O11 -> 89707
B12: 11 | C12: 45720 | D12: 24 | E12: 45757 | F12: 45748 | G12: Q1 | H12: Chandu Enterprises | I12: Remaining 50% for Material shade net | J12: Shade Net | K12: 14880 | M12: 14880 | O12: 7440 | P12: Ad-Hoc | Q12: Estate Management | T12: =N12+O12 -> 7440
B13: 12 | C13: 30-3-2025 | D13: 59 | E13: 45757 | F13: 45717 | G13: Q4 FY 24-25 | H13: Sri Venkateshwara Enterprises | I13: Charges towards cleaning garbage for the month of March | J13: Garbage Collection | K13: 95000 | L13: 17100 | M13: 112100 | N13: 950 | O13: 111150 | P13: Operating | Q13: Housekeeping & Waste | T13: =N13+O13 -> 112100
B14: 13 | C14: 45751 | D14: VS4-2025-26/014 | E14: 45757 | F14: 45717 | G14: Q4 FY 24-25 | H14: VS4 | I14: Security guard | J14: Security Management Fees | K14: 156850 | L14: 28233 | M14: 185083 | N14: 3137 | O14: 181946 | P14: Operating | Q14: Safety & Security | T14: =N14+O14 -> 185083
B15: 14 | C15: 45751 | D15: VS4-2025-26/013 | E15: 45757 | F15: 45717 | G15: Q4 FY 24-25 | H15: VS4 | I15: Fire Officer | J15: Security Management Fees | K15: 42233 | L15: 7602 | M15: 49835 | N15: 844.66 | O15: 48990 | P15: Operating | Q15: Safety & Security | T15: =N15+O15 -> 49834.66
B16: 15 | C16: 45751 | D16: VS4-2025-26/012 | E16: 45757 | F16: 45717 | G16: Q4 FY 24-25 | H16: VS4 | I16: security officer,supervisor,guard,CCTV Operator | J16: Security Management Fees | K16: 1590902 | L16: 286362 | M16: 1877264 | N16: 31818.03 | O16: 1845446 | P16: Operating | Q16: Safety & Security | T16: =N16+O16 -> 1877264
B17: 16 | C17: 28-03-2025 | D17: 222/24-25 | E17: 45757 | F17: 45748 | G17: Q1 | H17: Mukajjar Smarttech India | I17: West gate entry and exit,Amber block entry,east gate entry and exit | J17: West gate Entry and Exit Civil Works | K17: 96404 | L17: 17353 | M17: 113757 | N17: 1928.08 | O17: 111829 | P17: Capex | Q17: Civil & Lifts | T17: =N17+O17 -> 113757.08
B18: 17 | D18: Quotation | E18: 45757 | F18: 45748 | G18: Q1 | H18: Septron Machinaries | I18: 50% Advance forMulti disc screw press model-Blue STP Screw press system supply & Installation | J18: Screw Press Machine for STP-Blue | K18: 505000 | L18: 90900 | M18: 595900 | O18: 297950 | P18: Capex | Q18: Water & Sewage | T18: =N18+O18 -> 297950
B19: 18 | C19: 25-03-2025 | D19: 1438 | E19: 45763 | F19: 45717 | G19: Q4 FY 24-25 | H19: Genex Utility & Management | I19: Operation and maintenance charges | J19: STP/WTP Maint | K19: 352880 | L19: 63518 | M19: 416398 | N19: 7058 | O19: 409341 | P19: Operating | Q19: Water & Sewage | T19: =N19+O19 -> 416399
B20: 19 | C20: 14-04-2025 | D20: 19286 | E20: 45763 | F20: 45748 | G20: Q1 | H20: Sai suchith pest control | I20: Pyndor,fogging gas can | J20: Pest control Consumables | K20: 10590 | L20: 1906 | M20: 12496 | O20: 12496 | P20: Operating | Q20: Housekeeping & Waste | T20: =N20+O20 -> 12496
B21: 20 | C21: 45965 | E21: 45763 | F21: 45748 | G21: Q1 | H21: Balaji electricals and lights gallery | I21: Core cable | J21: Electrical Items | K21: 22340 | L21: 4021 | M21: 26361 | O21: 26361 | P21: Ad-Hoc | Q21: Electrical | T21: =N21+O21 -> 26361
B22: 24 | C22: 45964 | D22: Quotation | E22: 45768 | F22: 45748 | G22: Q1 | H22: Contrast Engineering Works | I22: 50% Advance for Donation Box Fabrication | J22: Fabrication - Donation Box | K22: 21000 | L22: 3780 | M22: 24780 | O22: 12390 | P22: Ad-Hoc | Q22: Estate Management | T22: =N22+O22 -> 12390
B23: 25 | C23: 14-04-2025 | D23: OP/25-26/016 | E23: 45768 | F23: 45748 | G23: Q1 | H23: Office Point | I23: Garbage Bag extra large, Mopstick metal rod | J23: Housekeeping Consumables | K23: 75024 | L23: 12687 | M23: 87711 | O23: 87711 | P23: Ad-Hoc | Q23: Estate Management | T23: =N23+O23 -> 87711
B24: 26 | C24: 15-04-2025 | D24: 26 | E24: 45768 | F24: 45748 | G24: Q1 | H24: Chandu enterprises | I24: Garware net | J24: Net | K24: 7200 | M24: 7200 | O24: 7200 | P24: Ad-Hoc | Q24: Estate Management | T24: =N24+O24 -> 7200
B25: 27 | C25: 45965 | D25: 22 | E25: 45768 | F25: 45748 | G25: Q1 | H25: Srinivas Agro Kendra | I25: Monocil,chorophyros,Tenget | J25: Landscaping Consumables | K25: 10510 | L25: 1892 | M25: 12402 | O25: 12402 | P25: Operating | Q25: Landscaping & ERT | T25: =N25+O25 -> 12402
B26: 28 | C26: 45965 | D26: 507 | E26: 45768 | F26: 45748 | G26: Q1 | H26: Srinivas Agro Kendra | I26: Cocopit | J26: Landscaping Consumables | K26: 3298 | M26: 3298 | O26: 3298 | P26: Operating | Q26: Landscaping & ERT | T26: =N26+O26 -> 3298
B27: 29 | C27: 14-04-2025 | D27: INV-25-26/0002 | E27: 45768 | F27: 45748 | G27: Q1 | H27: Agarwal & Shetty | I27: Book keeping charges | J27: Bookkeeping Services | K27: 89888 | L27: 16180 | M27: 106068 | N27: 8989 | O27: 97079 | P27: Operating | Q27: Finance & Accounts | T27: =N27+O27 -> 106068
B28: 30 | C28: 18-04-2025 | D28: 29 | E28: 45768 | F28: 45748 | G28: Q1 | H28: Harish Trading and Engineering | I28: Crimson Borewell Starter with auto phase | J28: Borewell | K28: 22010 | L28: 3962 | M28: 25972 | O28: 25972 | P28: Capex | Q28: Water & Sewage | T28: =N28+O28 -> 25972
B29: 31 | C29: 26-03-2025 | D29: Quotation | E29: 45768 | F29: 45748 | G29: Q1 | H29: Elon Facade | I29: 50% Advance for Eyebolt Fixing | J29: Eyebolt Fixing | K29: 15000 | M29: 15000 | O29: 7500 | P29: Ad-Hoc | Q29: Estate Management | T29: =N29+O29 -> 7500
B30: 32 | C30: 17-04-2025 | E30: 45768 | F30: 45748 | G30: Q1 | H30: Poonam Hardware & Electricals | I30: ACC Cement | J30: Plumbing Consumables | K30: 5000 | M30: 5000 | O30: 5000 | P30: Ad-Hoc | Q30: Water & Sewage | T30: =N30+O30 -> 5000
B31: 33 | C31: 19-04-2025 | E31: 45768 | F31: 45748 | G31: Q1 | H31: Poonam Hardware & Electricals | I31: Plumbing Material | J31: Plumbing Consumables | K31: 7300 | M31: 7300 | O31: 7300 | P31: Ad-Hoc | Q31: Water & Sewage | T31: =N31+O31 -> 7300
B32: 34 | E32: 45768 | F32: 45748 | G32: Q1 | H32: Mukajjar Smarttech India | I32: Crimson and Amber RWH Works | J32: RWH Works | K32: 1898631 | L32: 341754 | M32: 2240385 | O32: 653654 | P32: Capex | Q32: Civil & Lifts | T32: =N32+O32 -> 653654
B33: 35 | C33: 19-04-2025 | E33: 45770 | F33: 45748 | G33: Q1 | H33: Balaji electricals and lights gallery | I33: Silk cable | J33: Electrical Items | K33: 974 | L33: 176 | M33: 1150 | O33: 1150 | P33: Ad-Hoc | Q33: Electrical | T33: =N33+O33 -> 1150
B34: 36 | C34: 16-04-2025 | D34: 1924 | E34: 45770 | F34: 45748 | G34: Q1 | H34: Sri Maruthi Septic Cleaners | I34: Sewage sludge disposal from Blue Block STP | J34: STP- Sludge Removal | K34: 26650 | L34: 4797 | M34: 31447 | O34: 31447 | P34: Ad-Hoc | Q34: Water & Sewage | T34: =N34+O34 -> 31447
B35: 37 | C35: 13-04-2025 | E35: 45773 | F35: 45748 | G35: Q1 | H35: Balaji electricals and lights gallery | I35: Pipe, Bend, Core cable | J35: Electrical Items | K35: 4579 | L35: 824 | M35: 5403 | O35: 5403 | P35: Ad-Hoc | Q35: Electrical | T35: =N35+O35 -> 5403
B36: 38 | C36: 13-04-2025 | D36: 4 | E36: 45773 | F36: 45748 | G36: Q1 | H36: Moksha Distributors | I36: UP & Down Down light | J36: Electrical Items | K36: 4695 | L36: 845 | M36: 5540 | O36: 5540 | P36: Ad-Hoc | Q36: Electrical | T36: =N36+O36 -> 5540
B37: 39 | C37: 23-04-2025 | D37: IV-25-007 | E37: 45773 | F37: 45748 | G37: Q1 | H37: Elon Facade | I37: Remaining 50% for eye bolt fixing | J37: Eyebolt Fixing | K37: 15000 | L37: 2700 | M37: 17700 | O37: 10200 | P37: Ad-Hoc | Q37: Estate Management | T37: =N37+O37 -> 10200
B38: 40 | C38: 23-04-2025 | D38: Quotation | E38: 45773 | F38: 45748 | G38: Q1 | H38: Karnataka Motors Rewinding Co | I38: 50% Advance for lubi make monoblock pump Motor | J38: Motor Pump Service | K38: 26520 | M38: 26520 | O38: 13260 | P38: Ad-Hoc | Q38: Water & Sewage | T38: =N38+O38 -> 13260
B39: 41 | C39: 19-04-2025 | D39: 5 | E39: 45773 | F39: 45748 | G39: Q1 | H39: Om Enterprises | I39: Green protection Mesh | J39: Net | K39: 7195 | L39: 1295 | M39: 8490 | O39: 8490 | P39: Ad-Hoc | Q39: Housekeeping & Waste | T39: =N39+O39 -> 8490
B40: 42 | C40: 45775 | E40: 45775 | F40: 45748 | G40: Q1 | H40: ICICI | I40: Bank Charges | J40: Bank Charges | K40: 10 | L40: 2 | M40: 12 | O40: 12 | P40: Operating | Q40: Finance & Accounts | T40: =N40+O40 -> 12
B41: 43 | E41: 45762 | F41: 45717 | G41: Q4 FY 24-25 | H41: BESCOM | I41: BESCOM- Common Area March | J41: BESCOM Bills | K41: 769625 | M41: 769625 | O41: 769625 | P41: Operating | Q41: Electrical | T41: =N41+O41 -> 769625
B42: 45 | E42: 45783 | F42: 45778 | G42: Q1 | H42: Elon Facade | I42: Advance Facade cleaning | J42: Facade cleaning | K42: 550914 | L42: 99165 | M42: 650079 | O42: 75000 | P42: Operating | Q42: Estate Management | T42: =N42+O42 -> 75000
B43: 46 | C43: 22-04-2025 | D43: 1 | E43: 45783 | F43: 45717 | G43: Q4 FY 24-25 | H43: Urban Blossom | I43: Maintenance of Landscaped Garden for the month of March25 | J43: Gardening & Landscaping Management fees | K43: 450262 | L43: 81047 | M43: 531309 | N43: 4502.62 | O43: 526807 | P43: Operating | Q43: Landscaping & ERT | T43: =N43+O43 -> 531309.62
B44: 47 | C44: 25-04-2025 | D44: 4566 | E44: 45783 | F44: 45778 | G44: Q1 | H44: S R Office Suppliers | I44: Convex mirror purchased | J44: Purchase of Convex Mirror | K44: 9750 | L44: 1755 | M44: 11505 | O44: 11505 | P44: Ad-Hoc | Q44: Estate Management | T44: =N44+O44 -> 11505
B45: 48 | C45: 45965 | E45: 45783 | F45: 45778 | G45: Q1 | H45: SVS 3D Pool services | I45: Swimming pool filter services | J45: Swimming Pool Consumables | K45: 27000 | M45: 27000 | O45: 27000 | P45: Ad-Hoc | Q45: Water & Sewage | T45: =N45+O45 -> 27000
B46: 49 | C46: 30-04-2025 | D46: SMPI-06/25-26 | E46: 45783 | F46: 45778 | G46: Q1 | H46: Septron Machinaries | I46: Remaining payment for Multi disc screw press machine-Blue STP Screw press system supply & Installation | J46: Screw Press Machine for STP-Blue | K46: 505000 | L46: 90900 | M46: 595900 | O46: 297950 | P46: Capex | Q46: Water & Sewage | T46: =N46+O46 -> 297950
B47: 50 | C47: 30-04-2025 | D47: 252 | E47: 45783 | F47: 45748 | G47: Q1 | H47: Sree Sai Ganesh Minerals | I47: 20L Water Can | J47: Drinking Water Can | K47: 28168 | L47: 3380 | M47: 31548 | O47: 31548 | P47: Operating | Q47: Water & Sewage | T47: =N47+O47 -> 31548
B48: 51 | C48: 25-04-2025 | D48: 9387 | E48: 45783 | F48: 45778 | G48: Q1 | H48: Adnan Enterprises | I48: Dustbin FRP Duo | J48: Housekeeping Consumables | K48: 10600 | L48: 1908 | M48: 12508 | O48: 12508 | P48: Ad-Hoc | Q48: Housekeeping & Waste | T48: =N48+O48 -> 12508
B49: 52 | C49: 17-04-2025 | D49: 1788 | E49: 45783 | F49: 45778 | G49: Q1 | H49: S R Office Suppliers | I49: Rubber Hole Mate | J49: Housekeeping Consumables | K49: 6800 | L49: 1224 | M49: 8424 | O49: 8424 | P49: Ad-Hoc | Q49: Housekeeping & Waste | T49: =N49+O49 -> 8424
B50: 53 | C50: 45662 | D50: KLKA2526-05046 | E50: 45783 | F50: 45748 | G50: Q1 | H50: Kre38 Labs pvt ltd | I50: Waltr Monthly Subscription | J50: Water Level Meters | K50: 8980 | L50: 1616 | M50: 10596 | N50: 180 | O50: 10417 | P50: Operating | Q50: Water & Sewage | T50: =N50+O50 -> 10597
B51: 54 | C51: 20-04-2025 | D51: Quotation | E51: 45783 | F51: 45778 | G51: Q1 | H51: Pasolite Electric Co | I51: 50% Advance for DR016 LED Driver | J51: Electrical Items | K51: 32300 | L51: 5814 | M51: 38114 | O51: 19057 | P51: Ad-Hoc | Q51: Electrical | T51: =N51+O51 -> 19057
B52: 55 | C52: 30-04-2025 | D52: 1202 | E52: 45783 | F52: 45778 | G52: Q1 | H52: Jasvanth Singh Nursery | I52: Advance for china doll,Ficus,Lantana | J52: Garden & Landscaping Materials | K52: 93800 | M52: 93800 | O52: 93800 | P52: Operating | Q52: Landscaping & ERT | T52: =N52+O52 -> 93800
B53: 56 | C53: 30-04-2025 | D53: 9390 | E53: 45784 | F53: 45778 | G53: Q1 | H53: Adnan Enterprises | I53: Dustbin | J53: Housekeeping Consumables | K53: 39200 | L53: 7056 | M53: 46256 | O53: 46256 | P53: Ad-Hoc | Q53: Housekeeping & Waste | T53: =N53+O53 -> 46256
B54: 57 | C54: 21-04-2025 | E54: 45784 | F54: 45778 | G54: Q1 | H54: Sriyadevi Electricals and Hardware | I54: Anchor bolt | J54: Electrical Items | K54: 2500 | M54: 2500 | O54: 2500 | P54: Ad-Hoc | Q54: Estate Management | T54: =N54+O54 -> 2500
B55: 58 | C55: 45662 | D55: INV-25-26/0020 | E55: 45784 | F55: 45778 | G55: Q1 | H55: Agarwal & Shetty | I55: Book keeping charges | J55: Bookkeeping Services | K55: 89888 | L55: 16180 | M55: 106068 | N55: 8989 | O55: 97079 | P55: Operating | Q55: Finance & Accounts | T55: =N55+O55 -> 106068
B56: 59 | C56: 45662 | E56: 45784 | F56: 45778 | G56: Q1 | H56: Poonam Hardware & Electricals | I56: WC parts for Amber Staffroom | J56: Plumbing Consumables | K56: 2900 | M56: 2900 | O56: 2900 | P56: Ad-Hoc | Q56: Water & Sewage | T56: =N56+O56 -> 2900
B57: 60 | C57: 45662 | D57: 02/25-26 | E57: 45784 | F57: 45748 | G57: Q1 | H57: Sri Venkateshwara Enterprises | I57: Charges towards clearing Garbage | J57: Garbage Collection | K57: 103000 | L57: 18540 | M57: 121540 | N57: 1030 | O57: 120510 | P57: Operating | Q57: Housekeeping & Waste | T57: =N57+O57 -> 121540
B58: 61 | C58: 26-03-2025 | D58: Quotation | E58: 45784 | F58: 45778 | G58: Q1 | H58: Sahara Waterproofing | I58: 50% Advance for Concrete surface Cleaning/chipping/grinding | J58: Clubhouse Terrace & Swimming Pool water work | K58: 35000 | L58: 6300 | M58: 41300 | O58: 17500 | P58: Ad-Hoc | Q58: Estate Management | T58: =N58+O58 -> 17500
B59: 62 | C59: 45662 | D59: 012/25-26 | E59: 45784 | F59: 45778 | G59: Q1 | H59: Mukajjar Smarttech India | I59: Crimson RWH Civil works as per the annexure | J59: RWH Works | K59: 1941687 | L59: 349504 | M59: 2291191 | O59: 599256 | P59: Capex | Q59: Civil & Lifts | T59: =N59+O59 -> 599256
B60: 63 | C60: 45662 | D60: P1/8299/2025-26 | E60: 45784 | F60: 45778 | G60: Q1 | H60: Algo Hydro Tech | I60: Waste water cutter pump | J60: STP Water Cutter Pump | K60: 29408 | L60: 5293 | M60: 34701 | O60: 34701 | P60: Capex | Q60: Water & Sewage | T60: =N60+O60 -> 34701
B61: 64 | C61: 26-04-2025 | D61: 101 | E61: 45784 | F61: 45778 | G61: Q1 | H61: Assian Colling System | I61: GYM Room AC Servicing | J61: AC- Servicing | K61: 9750 | M61: 9750 | O61: 9750 | P61: Ad-Hoc | Q61: ClubHouse | T61: =N61+O61 -> 9750
B62: 65 | C62: 28-04-2025 | D62: 27 | E62: 45788 | F62: 45778 | G62: Q1 | H62: Blaze Design Tech | I62: Remaining payment for supply of conventional fire alaram | J62: Fire Alarm Installation | K62: 609170 | L62: 109651 | M62: 718821 | N62: 6091.7 | O62: 202992 | P62: Capex | Q62: Safety & Security | T62: =N62+O62 -> 209083.7
B63: 66 | C63: 45782 | D63: 19612 | E63: 45788 | F63: 45778 | G63: Q1 | H63: Sai Suchith Pest Control | I63: Pyndor, Fogging Gas can | J63: Pest control Consumables | K63: 13150 | L63: 2367 | M63: 15517 | O63: 15517 | P63: Operating | Q63: Housekeeping & Waste | T63: =N63+O63 -> 15517
B64: 67 | E64: 45783 | F64: 45778 | G64: Q1 | H64: Think Thanx | I64: CCTV AMC Charges for the month of April | J64: CCTV Maint | K64: 7500 | L64: 1350 | M64: 8850 | N64: 75 | O64: 8775 | P64: Operating | Q64: Safety & Security | T64: =N64+O64 -> 8850
B65: 68 | C65: 45662 | D65: IAC-17/37 | E65: 45788 | F65: 45748 | G65: Q1 | H65: Think Thanx | I65: CCTV AMC Charges for the month of April | J65: CCTV Maint | K65: 7500 | L65: 1350 | M65: 8850 | N65: 75 | O65: 8775 | P65: Operating | Q65: Safety & Security | T65: =N65+O65 -> 8850
B66: 69 | C66: 45721 | D66: 1208 | E66: 45788 | F66: 45778 | G66: Q1 | H66: Jasvanth Singh Nursery | I66: Creeper fig, Tecoma Orange, Pandanus | J66: Garden & Landscaping Materials | K66: 17350 | M66: 17350 | O66: 17350 | P66: Ad-Hoc | Q66: Landscaping & ERT | T66: =N66+O66 -> 17350
B67: 70 | C67: 45993 | D67: SWP/24/25/00038 | E67: 45788 | F67: 45778 | G67: Q1 | H67: Sahara Waterproofing | I67: 20% Advance for Swimming pool arae tile works | J67: Clubhouse Terrace & Swimming Pool water work | K67: 605530 | L67: 108995 | M67: 714525 | O67: 121106 | P67: Capex | Q67: Estate Management | T67: =N67+O67 -> 121106
B68: 71 | C68: 29-04-2025 | D68: 166 | E68: 45788 | F68: 45778 | G68: Q1 | H68: Contrast Engineering Works | I68: Remaining payment for Donation box Fabrication | J68: Fabrication - Donation Box | K68: 21000 | L68: 3780 | M68: 24780 | O68: 12390 | P68: Ad-Hoc | Q68: Estate Management | T68: =N68+O68 -> 12390
B69: 72 | C69: 45721 | D69: VS4-2025-26/PI009 | E69: 45788 | F69: 45748 | G69: Q1 | H69: VS4 | I69: Fire Officer, Service charge | J69: Security Management Fees | K69: 43411 | L69: 7814 | M69: 51225 | N69: 868 | O69: 50357 | P69: Operating | Q69: Safety & Security | T69: =N69+O69 -> 51225
B70: 73 | C70: 45721 | D70: VS4-2025-26/PI010 | E70: 45788 | F70: 45748 | G70: Q1 | H70: VS4 | I70: Security Guard, Service charge | J70: Security Management Fees | K70: 161644 | L70: 29096 | M70: 190739 | N70: 3233 | O70: 187507 | P70: Operating | Q70: Safety & Security | T70: =N70+O70 -> 190740
B71: 74 | C71: 45721 | D71: VS4-2025-26/PI008 | E71: 45790 | F71: 45748 | G71: Q1 | H71: VS4 | I71: Security officer, Security Supervisior, Head guard | J71: Security Management Fees | K71: 1646794 | L71: 296423 | M71: 1943217 | N71: 32935.88 | O71: 1910281 | P71: Operating | Q71: Safety & Security | T71: =N71+O71 -> 1943216.9
B72: 75 | C72: 45813 | D72: 2584 | E72: 45790 | F72: 45748 | G72: Q1 | H72: Genex Utility & Management | I72: Operation and Maintenance charges | J72: STP/WTP Maint | K72: 352880 | L72: 63518 | M72: 416398 | N72: 7058 | O72: 409341 | P72: Operating | Q72: Water & Sewage | T72: =N72+O72 -> 416399
B73: 76 | C73: 22-04-2025 | D73: 8 | E73: 45790 | F73: 45778 | G73: Q1 | H73: Moksha Distributors | I73: 50% Advance for LED Rope Light, LED Rope light cord | J73: Electrical Items | K73: 373260 | L73: 67187 | M73: 440447 | O73: 220223 | P73: Ad-Hoc | Q73: Electrical | T73: =N73+O73 -> 220223
B74: 77 | C74: 45874 | E74: 45790 | F74: 45778 | G74: Q1 | H74: Poonam Hardware & Electricals | I74: Amber STP Drain pump plumbing work | J74: Plumbing Consumables | K74: 5690 | M74: 5690 | O74: 5690 | P74: Ad-Hoc | Q74: Water & Sewage | T74: =N74+O74 -> 5690
B75: 78 | C75: 45905 | D75: 35 | E75: 45790 | F75: 45778 | G75: Q1 | H75: Siri Aishwarya Nursery and gardening | I75: Buffalo Grass(Shade Grass) | J75: Landscaping Consumables | K75: 7000 | L75: 270 | M75: 7270 | O75: 7270 | P75: Operating | Q75: Landscaping & ERT | T75: =N75+O75 -> 7270
B76: 79 | C76: 45874 | D76: 34 | E76: 45790 | F76: 45778 | G76: Q1 | H76: Siri Aishwarya Nursery and gardening | I76: Mexican Grass | J76: Landscaping Consumables | K76: 129500 | L76: 3150 | M76: 132650 | O76: 132650 | P76: Operating | Q76: Landscaping & ERT | T76: =N76+O76 -> 132650
B77: 80 | D77: VR MAY 25-26 0144 | E77: 45791 | F77: 45748 | G77: Q1 | H77: V R FACILITY SERVICES | I77: EM | J77: VRFS- Estate Management | K77: 72540 | L77: 13057.2 | M77: 85597.2 | N77: 725.4 | O77: 84871.8 | P77: Operating | Q77: Estate Management | T77: =N77+O77 -> 85597.2
B78: 81 | D78: VR MAY 25-26 0144 | E78: 45791 | F78: 45748 | G78: Q1 | H78: V R FACILITY SERVICES | I78: Technical Manager | J78: VRFS- Estate Management | K78: 50000 | L78: 9000 | M78: 59000 | N78: 500 | O78: 58500 | P78: Operating | Q78: Estate Management | T78: =N78+O78 -> 59000
B79: 82 | D79: VR MAY 25-26 0144 | E79: 45791 | F79: 45748 | G79: Q1 | H79: V R FACILITY SERVICES | I79: Store Executive | J79: VRFS- Estate Management | K79: 29696 | L79: 5345.28 | M79: 35041.28 | N79: 296.96 | O79: 34744.32 | P79: Operating | Q79: Estate Management | T79: =N79+O79 -> 35041.28
B80: 83 | D80: VR MAY 25-26 0144 | E80: 45791 | F80: 45748 | G80: Q1 | H80: V R FACILITY SERVICES | I80: Assistant Property Manager (Softservices) | J80: VRFS- Estate Management | K80: 47520 | L80: 8553.6 | M80: 56073.6 | N80: 475.2 | O80: 55598.4 | P80: Operating | Q80: Estate Management | T80: =N80+O80 -> 56073.6
B81: 84 | D81: VR MAY 25-26 0144 | E81: 45791 | F81: 45748 | G81: Q1 | H81: V R FACILITY SERVICES | I81: Helpdesk Exective | J81: VRFS- Estate Management | K81: 30780 | L81: 5540.4 | M81: 36320.4 | N81: 307.8 | O81: 36012.6 | P81: Operating | Q81: Estate Management | T81: =N81+O81 -> 36320.4
B82: 85 | D82: VR MAY 25-26 0144 | E82: 45791 | F82: 45748 | G82: Q1 | H82: V R FACILITY SERVICES | I82: Electricians | J82: VRFS- Electricians | K82: 181556 | L82: 32680.08 | M82: 214236.08 | N82: 1815.56 | O82: 212420.52 | P82: Operating | Q82: Electrical | T82: =N82+O82 -> 214236.08
B83: 86 | D83: VR MAY 25-26 0144 | E83: 45791 | F83: 45748 | G83: Q1 | H83: V R FACILITY SERVICES | I83: Sr. Plumbers | J83: VRFS- Plumbers | K83: 204195 | L83: 36755.1 | M83: 240950.1 | N83: 2041.95 | O83: 238908.15 | P83: Operating | Q83: Water & Sewage | T83: =N83+O83 -> 240950.1
B84: 87 | D84: VR MAY 25-26 0144 | E84: 45791 | F84: 45748 | G84: Q1 | H84: V R FACILITY SERVICES | I84: Carpenter | J84: VRFS- Carpenters & Multi Technician | K84: 25200 | L84: 4536 | M84: 29736 | N84: 252 | O84: 29484 | P84: Operating | Q84: Civil & Lifts | T84: =N84+O84 -> 29736
B85: 88 | D85: VR MAY 25-26 0144 | E85: 45791 | F85: 45748 | G85: Q1 | H85: V R FACILITY SERVICES | I85: Multi Technician/ Handiman | J85: VRFS- Carpenters & Multi Technician | K85: 28050 | L85: 5049 | M85: 33099 | N85: 280.5 | O85: 32818.5 | P85: Operating | Q85: Civil & Lifts | T85: =N85+O85 -> 33099
B86: 89 | D86: VR MAY 25-26 0144 | E86: 45791 | F86: 45748 | G86: Q1 | H86: V R FACILITY SERVICES | I86: House Keeping Supervisor | J86: VRFS-Housekeeping Salary | K86: 26667 | L86: 4800.06 | M86: 31467.06 | N86: 266.67 | O86: 31200.39 | P86: Operating | Q86: Housekeeping & Waste | T86: =N86+O86 -> 31467.06
B87: 90 | D87: VR MAY 25-26 0144 | E87: 45791 | F87: 45748 | G87: Q1 | H87: V R FACILITY SERVICES | I87: House Keepers | J87: VRFS-Housekeeping Salary | K87: 571805 | L87: 102924.9 | M87: 674729.9 | N87: 5718.05 | O87: 664170.85 | P87: Operating | Q87: Housekeeping & Waste | T87: =N87+O87 -> 669888.9
B88: 91 | D88: VR MAY 25-26 0144 | E88: 45791 | F88: 45748 | G88: Q1 | H88: V R FACILITY SERVICES | I88: Equipment Cost | J88: VRFS-Housekeeping Salary | K88: 20000 | L88: 3600 | M88: 23600 | N88: 200 | O88: 23400 | P88: Operating | Q88: Housekeeping & Waste | T88: =N88+O88 -> 23600
... B90: 93 | D90: VR MAY 25-26 0144 | E90: 45791 | F90: 45748 | G90: Q1 | H90: V R FACILITY SERVICES | I90: Pest Control Management | J90: VRFS-Housekeeping Salary | K90: 1640122 | L90: 295221.96 | M90: 1935344 | N90: 367.2 | O90: 42962.4 | P90: Operating | Q90: Housekeeping & Waste | T90: =N90+O90 -> 43329.6
B91: 94 | D91: VR MAY 25-26 0144 | E91: 45791 | F91: 45748 | G91: Q1 | H91: V R FACILITY SERVICES | I91: Management Fees | J91: VRFS- Estate Management | P91: Operating | Q91: Estate Management | T91: =N91+O91 -> 0
B92: 95 | C92: 45721 | D92: IV-25-05 | E92: 45792 | F92: 45778 | G92: Q1 | H92: Elon Facade | I92: Remaining payment for Facade cleaning | J92: Facade cleaning | K92: 550914 | L92: 99164 | M92: 650078 | N92: 5509.14 | O92: 294112 | P92: Operating | Q92: Estate Management | T92: =N92+O92 -> 299621.14
B93: 96 | E93: 45792 | F93: 45689 | G93: Q1 | H93: Agarwal & Shetty | I93: Professional tax for the year 2025-26 | J93: Bookkeeping Services | K93: 2500 | M93: 2500 | O93: 2500 | P93: Operating | Q93: Finance & Accounts | T93: =N93+O93 -> 2500
B94: 97 | C94: 22/04/2025 | D94: Quotation | E94: 45797 | F94: 45778 | G94: Q1 | H94: Blaze Design Tech | I94: 50% Advance for Supply of conventional fire alaram with accessories | J94: Fire Alarm Installation | K94: 419615 | L94: 75531 | M94: 495146 | N94: 4196 | O94: 243377 | P94: Capex | Q94: Safety & Security | T94: =N94+O94 -> 247573
B95: 98 | C95: 45996 | D95: 387 | E95: 45797 | F95: 45778 | G95: Q1 | H95: Om Enterprises | I95: Garbage cover Large, Mop clip, Mop stick | J95: Housekeeping Consumables | K95: 78659 | L95: 13425 | M95: 92085 | O95: 92085 | P95: Ad-Hoc | Q95: Housekeeping & Waste | T95: =N95+O95 -> 92085
B96: 99 | C96: 14-05-2025 | D96: 37 | E96: 45797 | F96: 45778 | G96: Q1 | H96: Siri Aishwarya Nursery and gardening | I96: Buffalo Grass(Shade Grass) | J96: Landscaping Consumables | K96: 9750 | L96: 270 | M96: 10020 | O96: 10020 | P96: Operating | Q96: Landscaping & ERT | T96: =N96+O96 -> 10020
B97: 100 | C97: 13-05-2025 | D97: 36 | E97: 45797 | F97: 45778 | G97: Q1 | H97: Siri Aishwarya Nursery and gardening | I97: Buffalo Grass(Shade Grass) | J97: Landscaping Consumables | K97: 5350 | L97: 270 | M97: 5620 | O97: 5620 | P97: Operating | Q97: Landscaping & ERT | T97: =N97+O97 -> 5620
B98: 101 | C98: 45996 | D98: 1455 | E98: 45797 | F98: 45778 | G98: Q1 | H98: Jasvanth Singh Nursery | I98: Spider Lily, Eranthimum | J98: Garden & Landscaping Materials | K98: 16300 | M98: 16300 | O98: 16300 | P98: Ad-Hoc | Q98: Landscaping & ERT | T98: =N98+O98 -> 16300
B99: 102 | C99: 45996 | D99: 1204 | E99: 45797 | F99: 45778 | G99: Q1 | H99: Jasvanth Singh Nursery | I99: Foxtail ferm, Ficus,Bird of paradise | J99: Garden & Landscaping Materials | K99: 38450 | M99: 38450 | O99: 38450 | P99: Ad-Hoc | Q99: Landscaping & ERT | T99: =N99+O99 -> 38450
B100: 103 | D100: Quotation | E100: 45797 | F100: 45778 | G100: Q1 | H100: Mukajjar Smarttech India | I100: 30% Advance for External precast compound wall, Landscaping | J100: External Precast Compound wall | K100: 5288286 | L100: 951891 | M100: 6240177 | N100: 52882.86 | O100: 1533603 | P100: Capex | Q100: Civil & Lifts | T100: =N100+O100 -> 1586485.9
B101: 104 | C101: 15-05-2025 | E101: 45797 | F101: 45778 | G101: Q1 | H101: Poonam Hardware & Electricals | I101: Blue STP Screw press and crimson rain water plumbing material | J101: Plumbing Consumables | K101: 8934 | M101: 8934 | O101: 8934 | P101: Ad-Hoc | Q101: Water & Sewage | T101: =N101+O101 -> 8934
...

Sheet OPEX Budget
A1: Nature | B1: Amount | C1: Quarter
A2: Water & Sewage | B2: 5108241 | C2: Q3 | P2: Q1 | Q2: Q2 | R2: Q3 | S2: Q4
A3: Civil & Lifts | B3: 1613900.1 | C3: Q3 | P3: Operating
A4: Electrical | B4: 4941421.3 | C4: Q3 | O4: Civil & Lifts | P4: =SUMIFS('1. Maint Account'!T:T,'1. Maint Account'!Q:Q,'OPEX Budget'!O4,'1. Maint Account'!P:P,'OPEX Budget'!$P$3,'1. Maint Account'!G:G,"Q1") -> 1502437.8 | Q4: =SUMIFS('1. Maint Account'!T:T,'1. Maint Account'!Q:Q,'OPEX Budget'!O4,'1. Maint Account'!P:P,'OPEX Budget'!$P$3,'1. Maint Account'!G:G,"Q2") -> 1423952.3 | R4: =SUMIFS('1. Maint Account'!T:T,'1. Maint Account'!Q:Q,'OPEX Budget'!O4,'1. Maint Account'!P:P,'OPEX Budget'!$P$3,'1. Maint Account'!G:G,"Q3") -> 867538.88
A5: Housekeeping & Waste | B5: 3564038.2 | C5: Q3 | O5: Water & Sewage | P5: =SUMIFS('1. Maint Account'!T:T,'1. Maint Account'!Q:Q,'OPEX Budget'!O5,'1. Maint Account'!P:P,'OPEX Budget'!$P$3,'1. Maint Account'!G:G,"Q1") -> 2209323.6 | Q5: =SUMIFS('1. Maint Account'!T:T,'1. Maint Account'!Q:Q,'OPEX Budget'!O5,'1. Maint Account'!P:P,'OPEX Budget'!$P$3,'1. Maint Account'!G:G,"Q2") -> 2156778.5 | R5: =SUMIFS('1. Maint Account'!T:T,'1. Maint Account'!Q:Q,'OPEX Budget'!O5,'1. Maint Account'!P:P,'OPEX Budget'!$P$3,'1. Maint Account'!G:G,"Q3") -> 1441060.8
A6: ClubHouse | B6: 86939.788 | C6: Q3 | O6: Safety & Security | P6: =SUMIFS('1. Maint Account'!T:T,'1. Maint Account'!Q:Q,'OPEX Budget'!O6,'1. Maint Account'!P:P,'OPEX Budget'!$P$3,'1. Maint Account'!G:G,"Q1") -> 6553327.7 | Q6: =SUMIFS('1. Maint Account'!T:T,'1. Maint Account'!Q:Q,'OPEX Budget'!O6,'1. Maint Account'!P:P,'OPEX Budget'!$P$3,'1. Maint Account'!G:G,"Q2") -> 6742150.8 | R6: =SUMIFS('1. Maint Account'!T:T,'1. Maint Account'!Q:Q,'OPEX Budget'!O6,'1. Maint Account'!P:P,'OPEX Budget'!$P$3,'1. Maint Account'!G:G,"Q3") -> 4106979
A7: Safety & Security | B7: 7311042.3 | C7: Q3 | O7: Estate Management | P7: =SUMIFS('1. Maint Account'!T:T,'1. Maint Account'!Q:Q,'OPEX Budget'!O7,'1. Maint Account'!P:P,'OPEX Budget'!$P$3,'1. Maint Account'!G:G,"Q1") -> 1367948.8 | Q7: =SUMIFS('1. Maint Account'!T:T,'1. Maint Account'!Q:Q,'OPEX Budget'!O7,'1. Maint Account'!P:P,'OPEX Budget'!$P$3,'1. Maint Account'!G:G,"Q2") -> 1060973.4 | R7: =SUMIFS('1. Maint Account'!T:T,'1. Maint Account'!Q:Q,'OPEX Budget'!O7,'1. Maint Account'!P:P,'OPEX Budget'!$P$3,'1. Maint Account'!G:G,"Q3") -> 1163769.9
A8: Landscaping & ERT | B8: 1747775.6 | C8: Q3 | O8: Housekeeping & Waste | P8: =SUMIFS('1. Maint Account'!T:T,'1. Maint Account'!Q:Q,'OPEX Budget'!O8,'1. Maint Account'!P:P,'OPEX Budget'!$P$3,'1. Maint Account'!G:G,"Q1") -> 2857521.4 | Q8: =SUMIFS('1. Maint Account'!T:T,'1. Maint Account'!Q:Q,'OPEX Budget'!O8,'1. Maint Account'!P:P,'OPEX Budget'!$P$3,'1. Maint Account'!G:G,"Q2") -> 2559429.2 | R8: =SUMIFS('1. Maint Account'!T:T,'1. Maint Account'!Q:Q,'OPEX Budget'!O8,'1. Maint Account'!P:P,'OPEX Budget'!$P$3,'1. Maint Account'!G:G,"Q3") -> 2060479.4
A9: Estate Management | B9: 1956374.4 | C9: Q3 | O9: Electrical | P9: =SUMIFS('1. Maint Account'!T:T,'1. Maint Account'!Q:Q,'OPEX Budget'!O9,'1. Maint Account'!P:P,'OPEX Budget'!$P$3,'1. Maint Account'!G:G,"Q1") -> 3136437.4 | Q9: =SUMIFS('1. Maint Account'!T:T,'1. Maint Account'!Q:Q,'OPEX Budget'!O9,'1. Maint Account'!P:P,'OPEX Budget'!$P$3,'1. Maint Account'!G:G,"Q2") -> 3860591.2 | R9: =SUMIFS('1. Maint Account'!T:T,'1. Maint Account'!Q:Q,'OPEX Budget'!O9,'1. Maint Account'!P:P,'OPEX Budget'!$P$3,'1. Maint Account'!G:G,"Q3") -> 2363576
A10: Finance & Accounts | B10: 343301.96 | C10: Q3 | O10: Landscaping & ERT | P10: =SUMIFS('1. Maint Account'!T:T,'1. Maint Account'!Q:Q,'OPEX Budget'!O10,'1. Maint Account'!P:P,'OPEX Budget'!$P$3,'1. Maint Account'!G:G,"Q1") -> 1862731.4 | Q10: =SUMIFS('1. Maint Account'!T:T,'1. Maint Account'!Q:Q,'OPEX Budget'!O10,'1. Maint Account'!P:P,'OPEX Budget'!$P$3,'1. Maint Account'!G:G,"Q2") -> 1582255 | R10: =SUMIFS('1. Maint Account'!T:T,'1. Maint Account'!Q:Q,'OPEX Budget'!O10,'1. Maint Account'!P:P,'OPEX Budget'!$P$3,'1. Maint Account'!G:G,"Q3") -> 1091180.6
A11: Total | B11: =SUM(B2:B10) -> 26673035 | C11: Q3 | O11: Finance & Accounts | P11: =SUMIFS('1. Maint Account'!T:T,'1. Maint Account'!Q:Q,'OPEX Budget'!O11,'1. Maint Account'!P:P,'OPEX Budget'!$P$3,'1. Maint Account'!G:G,"Q1") -> 468239.8 | Q11: =SUMIFS('1. Maint Account'!T:T,'1. Maint Account'!Q:Q,'OPEX Budget'!O11,'1. Maint Account'!P:P,'OPEX Budget'!$P$3,'1. Maint Account'!G:G,"Q2") -> 424531.28 | R11: =SUMIFS('1. Maint Account'!T:T,'1. Maint Account'!Q:Q,'OPEX Budget'!O11,'1. Maint Account'!P:P,'OPEX Budget'!$P$3,'1. Maint Account'!G:G,"Q3") -> 212171.24
O12: ClubHouse | P12: =SUMIFS('1. Maint Account'!T:T,'1. Maint Account'!Q:Q,'OPEX Budget'!O12,'1. Maint Account'!P:P,'OPEX Budget'!$P$3,'1. Maint Account'!G:G,"Q1") -> 138303.13 | Q12: =SUMIFS('1. Maint Account'!T:T,'1. Maint Account'!Q:Q,'OPEX Budget'!O12,'1. Maint Account'!P:P,'OPEX Budget'!$P$3,'1. Maint Account'!G:G,"Q2") -> 84200.932 | R12: =SUMIFS('1. Maint Account'!T:T,'1. Maint Account'!Q:Q,'OPEX Budget'!O12,'1. Maint Account'!P:P,'OPEX Budget'!$P$3,'1. Maint Account'!G:G,"Q3") -> 94400
P13: =SUM(P4:P12) -> 20096271 | Q13: =SUM(Q4:Q12) -> 19894863 | R13: =SUM(R4:R12) -> 13401156
A14: Water & Sewage | B14: 3696782 | C14: Q1
A15: Civil & Lifts | B15: 1615896 | C15: Q1
A16: Electrical | B16: 5898302 | C16: Q1
A17: Housekeeping & Waste | B17: 3087334 | C17: Q1
A18: ClubHouse | B18: 72345 | C18: Q1
A19: Safety & Security | B19: 7288876 | C19: Q1
A20: Landscaping & ERT | B20: 1742477 | C20: Q1
A21: Estate Management | B21: 1585633 | C21: Q1
A22: Finance & Accounts | B22: 322887 | C22: Q1
A23: Total | B23: =SUM(B14:B22) -> 25310532 | C23: Q1
A25: Water & Sewage | B25: 4496127 | C25: Q2
A26: Civil & Lifts | B26: 1565877.4 | C26: Q2
A27: Electrical | B27: 4885353.1 | C27: Q2
A28: Housekeeping & Waste | B28: 1491303.6 | C28: Q2
A29: ClubHouse | B29: 29002.1 | C29: Q2
A30: Safety & Security | B30: 7407870.4 | C30: Q2
A31: Landscaping & ERT | B31: 1770923.3 | C31: Q2
A32: Estate Management | B32: 886861.16 | C32: Q2
A33: Finance & Accounts | B33: 347848.68 | C33: Q2
A34: Total | B34: =SUM(B25:B33) -> 22881167 | C34: Q2
A36: Water & Sewage | B36: 4085895.8 | C36: Q4
A37: Civil & Lifts | B37: 1906166.3 | C37: Q4
A38: Electrical | B38: 4895833 | C38: Q4
A39: Housekeeping & Waste | B39: 3557939 | C39: Q4
A40: ClubHouse | B40: 82592.665 | C40: Q4
A41: Safety & Security | B41: 6695499.6 | C41: Q4
A42: Landscaping & ERT | B42: 1756111.3 | C42: Q4
A43: Estate Management | B43: 1816721.1 | C43: Q4
A44: Finance & Accounts | B44: 362185.71 | C44: Q4
A45: Total | B45: =SUM(B36:B44) -> 25158944 | C45: Q4

Sheet Capex Budget
A1: Nature | B1: Amount | C1: Quarter
A2: Fire Alarm Installation | B2: 0 | C2: Q1
A3: Park-plus Services | B3: 0 | C3: Q1
A4: West gate Entry and Exit Civil Works | B4: 0 | C4: Q1
A5: Screw Press Machine for STP-Blue | B5: 0 | C5: Q1
A6: Borewell | B6: 0 | C6: Q1
A7: RWH Works | B7: 0 | C7: Q1
A8: STP Water Cutter Pump | B8: 0 | C8: Q1
A9: Clubhouse Terrace & Swimming Pool water work | B9: 0 | C9: Q1
A10: External Precast Compound wall | B10: 0 | C10: Q1
A11: Lift/UPS Batteries | B11: 0 | C11: Q1
A12: CH - Civil Work | B12: 0 | C12: Q1
A13: East Wall Civil Works | B13: 0 | C13: Q1
... A38: Dumbells for Gym | B38: 0 | C38: Q3
